[
  {
    "id": "Your question...",
    "defaultMessage": "Your question..."
  },
  {
    "id": "Some additional info or comments (optional)",
    "defaultMessage": "Some additional info or comments (optional)"
  },
  {
    "id": "An answer var",
    "defaultMessage": "An answer var"
  },
  {
    "id": "Quiz questions",
    "defaultMessage": "Quiz questions"
  },
  {
    "id": "Add another question",
    "defaultMessage": "Add another question"
  },
  {
    "id": "Type: One of many",
    "defaultMessage": "Type: One of many"
  },
  {
    "id": "Show question to the client",
    "defaultMessage": "Show question to the client"
  },
  {
    "id": "Answers",
    "defaultMessage": "Answers"
  },
  {
    "id": "Add answer",
    "defaultMessage": "Add answer"
  }
]